wardy_utils/__init__.py
wardy_utils/log.py
wardy_utils/py.typed
wardy_utils/web.py
wardy_utils-0.5.2.dist-info/WHEEL
wardy_utils-0.5.2.dist-info/METADATA
wardy_utils-0.5.2.dist-info/RECORD
