Metadata-Version: 2.4
Name: wardy-utils
Version: 0.5.2
Summary: General Utilities
Author: Wardy
Author-email: Wardy <wardy3+gitlab@gmail.com>
License-Expression: MIT
Classifier: Development Status :: 4 - Beta
Classifier: Intended Audience :: Developers
Classifier: License :: OSI Approved :: MIT License
Classifier: Operating System :: OS Independent
Classifier: Programming Language :: Python :: 3
Classifier: Programming Language :: Python :: 3.14
Classifier: Topic :: Software Development :: Libraries :: Python Modules
Classifier: Typing :: Typed
Requires-Dist: pydantic-settings>=2.12.0
Requires-Dist: loguru>=0.7.3 ; extra == 'log'
Requires-Dist: hishel[httpx]>=1.1.8 ; extra == 'web'
Requires-Dist: httpx[brotli,http2,zstd]>=0.28.1 ; extra == 'web'
Requires-Python: >=3.14
Provides-Extra: log
Provides-Extra: web
